README.md
setup.py
cloud_toolkit_aws/__init__.py
cloud_toolkit_aws/_utilities.py
cloud_toolkit_aws/provider.py
cloud_toolkit_aws/pulumi-plugin.json
cloud_toolkit_aws/py.typed
cloud_toolkit_aws.egg-info/PKG-INFO
cloud_toolkit_aws.egg-info/SOURCES.txt
cloud_toolkit_aws.egg-info/dependency_links.txt
cloud_toolkit_aws.egg-info/not-zip-safe
cloud_toolkit_aws.egg-info/requires.txt
cloud_toolkit_aws.egg-info/top_level.txt
cloud_toolkit_aws/commons/__init__.py
cloud_toolkit_aws/commons/certificate.py
cloud_toolkit_aws/databases/__init__.py
cloud_toolkit_aws/databases/_enums.py
cloud_toolkit_aws/databases/_inputs.py
cloud_toolkit_aws/databases/aurora_mysql.py
cloud_toolkit_aws/databases/mysql.py
cloud_toolkit_aws/email/__init__.py
cloud_toolkit_aws/email/_enums.py
cloud_toolkit_aws/email/_inputs.py
cloud_toolkit_aws/email/email_sender.py
cloud_toolkit_aws/email/outputs.py
cloud_toolkit_aws/kubernetes/__init__.py
cloud_toolkit_aws/kubernetes/_enums.py
cloud_toolkit_aws/kubernetes/_inputs.py
cloud_toolkit_aws/kubernetes/adot_application.py
cloud_toolkit_aws/kubernetes/adot_operator.py
cloud_toolkit_aws/kubernetes/application_addon.py
cloud_toolkit_aws/kubernetes/argo_cd.py
cloud_toolkit_aws/kubernetes/aws_ebs_csi_driver.py
cloud_toolkit_aws/kubernetes/aws_load_balancer_controller.py
cloud_toolkit_aws/kubernetes/aws_secrets_store_csi_driver.py
cloud_toolkit_aws/kubernetes/calico.py
cloud_toolkit_aws/kubernetes/cert_manager.py
cloud_toolkit_aws/kubernetes/cluster.py
cloud_toolkit_aws/kubernetes/cluster_addons.py
cloud_toolkit_aws/kubernetes/cluster_admins.py
cloud_toolkit_aws/kubernetes/cluster_autoscaler.py
cloud_toolkit_aws/kubernetes/dashboard.py
cloud_toolkit_aws/kubernetes/external_dns.py
cloud_toolkit_aws/kubernetes/fluentbit.py
cloud_toolkit_aws/kubernetes/iam_authenticator.py
cloud_toolkit_aws/kubernetes/ingress_nginx.py
cloud_toolkit_aws/kubernetes/irsa.py
cloud_toolkit_aws/kubernetes/node_group.py
cloud_toolkit_aws/kubernetes/project.py
cloud_toolkit_aws/kubernetes/secrets_store_csi_driver.py
cloud_toolkit_aws/landingzone/__init__.py
cloud_toolkit_aws/landingzone/_inputs.py
cloud_toolkit_aws/landingzone/account_iam.py
cloud_toolkit_aws/landingzone/audit_logging.py
