Metadata-Version: 2.1
Name: cloud-toolkit-aws
Version: 0.13.0
License: Apache-2.0
Keywords: pulumi aws cloud-toolkit category/cloud kind/component
